yellowsapphire_sdk/__init__.py
yellowsapphire_sdk/api_client.py
yellowsapphire_sdk/api_response.py
yellowsapphire_sdk/configuration.py
yellowsapphire_sdk/exceptions.py
yellowsapphire_sdk/py.typed
yellowsapphire_sdk/rest.py
yellowsapphire_sdk/api/__init__.py
yellowsapphire_sdk/api/admin_customer_management_api.py
yellowsapphire_sdk/api/admin_inventory_management_api.py
yellowsapphire_sdk/api/admin_invoice_management_api.py
yellowsapphire_sdk/api/admin_order_fulfillment_api.py
yellowsapphire_sdk/api/admin_platform_configuration_api.py
yellowsapphire_sdk/api/admin_product_management_api.py
yellowsapphire_sdk/api/admin_system_management_api.py
yellowsapphire_sdk/api/admin_system_monitoring_api.py
yellowsapphire_sdk/api/customer_account_management_api.py
yellowsapphire_sdk/api/customer_order_management_api.py
yellowsapphire_sdk/api/customer_product_catalog_api.py
yellowsapphire_sdk/api/customer_shopping_cart_api.py
yellowsapphire_sdk/api/system_health_api.py
yellowsapphire_sdk/models/__init__.py
yellowsapphire_sdk/models/ad_banner.py
yellowsapphire_sdk/models/add_rating200_response.py
yellowsapphire_sdk/models/add_rating200_response_follow_up.py
yellowsapphire_sdk/models/add_rating200_response_rating.py
yellowsapphire_sdk/models/add_rating400_response.py
yellowsapphire_sdk/models/add_rating401_response.py
yellowsapphire_sdk/models/add_rating_request.py
yellowsapphire_sdk/models/add_to_cart200_response.py
yellowsapphire_sdk/models/add_to_cart200_response_cart_inner.py
yellowsapphire_sdk/models/add_to_cart404_response.py
yellowsapphire_sdk/models/add_to_cart500_response.py
yellowsapphire_sdk/models/add_to_cart_request.py
yellowsapphire_sdk/models/adjust_product_stock200_response.py
yellowsapphire_sdk/models/adjust_product_stock200_response_data.py
yellowsapphire_sdk/models/adjust_product_stock400_response.py
yellowsapphire_sdk/models/adjust_product_stock404_response.py
yellowsapphire_sdk/models/adjust_product_stock500_response.py
yellowsapphire_sdk-1.0.7.dist-info/METADATA
yellowsapphire_sdk-1.0.7.dist-info/WHEEL
yellowsapphire_sdk-1.0.7.dist-info/top_level.txt
yellowsapphire_sdk-1.0.7.dist-info/RECORD
